mcp_cmpay/__init__.py
mcp_cmpay/api_calls.py
mcp_cmpay/config.py
mcp_cmpay/encryption.py
mcp_cmpay/mcp_logger.py
mcp_cmpay/order_type.py
mcp_cmpay/server.py
mcp_cmpay-0.2.1.dist-info/METADATA
mcp_cmpay-0.2.1.dist-info/WHEEL
mcp_cmpay-0.2.1.dist-info/entry_points.txt
mcp_cmpay-0.2.1.dist-info/RECORD
