Metadata-Version: 2.4
Name: mcp-cmpay
Version: 0.2.1
Summary: 中国移动支付(China Mobile Pay) MCP Server 服务
Requires-Python: >=3.11
Requires-Dist: cryptography==44.0.3
Requires-Dist: httpx>=0.28.1
Requires-Dist: mcp[cli]==1.8.0
